avro_utils/__init__.py
avro_utils/avro_schema.py
avro_utils/avro_types.py
pfb/__init__.py
pfb/base.py
pfb/cli.py
pfb/reader.py
pfb/schema.py
pfb/writer.py
pfb/commands/__init__.py
pfb/commands/add.py
pfb/commands/rename.py
pfb/commands/show.py
pfb/exporters/__init__.py
pfb/exporters/gremlin.py
pfb/importers/__init__.py
pfb/importers/gen3dict.py
pfb/importers/json.py
python_pfb_sdk/__init__.py
python_pfb_sdk/__main__.py
python_pfb_sdk/file.py
python_pfb_sdk/reader.py
python_pfb_sdk/writer.py
tests/__init__.py
tests/conftest.py
tests/test_commands.py
utils/__init__.py
utils/dictionary.py
python_pfb_sdk-0.0.1.dist-info/LICENSE
python_pfb_sdk-0.0.1.dist-info/METADATA
python_pfb_sdk-0.0.1.dist-info/NOTICE
python_pfb_sdk-0.0.1.dist-info/WHEEL
python_pfb_sdk-0.0.1.dist-info/entry_points.txt
python_pfb_sdk-0.0.1.dist-info/top_level.txt
python_pfb_sdk-0.0.1.dist-info/RECORD
